doan2/arbiter/comparator/max_sel.v
module max_sel
(
    input       [1:0]       in1,in2,
    output      [1:0]       out,
    output                  sel
);

assign sel= (in1[1]&!in2[1])|(in1[0]&!in2[1]&!in2[0])|(in1[1]&in1[0]&!in2[0]);
assign out= sel?in1:in2;

endmodule

doan2/arbiter/comparator/max_sel_tb.v
`include "max_sel.v"
`timescale 1ns/1ns

module max_sel_tb
();

reg       [1:0]       in1,in2;
wire      [1:0]       out;
wire                  sel;

max_sel a( .in1(in1), .in2(in2), .out(out), .sel(sel));

initial begin

$dumpfile("max_sel_tb.vcd");
$dumpvars(0,max_sel_tb);

#10
in1='b00;
in2='b00;
#10
in1='b00;
in2='b01;
#10
in1='b00;
in2='b10;
#10
in1='b00;
in2='b11;
#10
in1='b01;
in2='b00;
#10
in1='b01;
in2='b01;
#10
in1='b01;
in2='b10;
#10
in1='b01;
in2='b11;
#10
in1='b10;
in2='b00;
#10
in1='b10;
in2='b01;
#10
in1='b10;
in2='b10;
#10
in1='b10;
in2='b11;
#10
in1='b11;
in2='b00;
#10
in1='b11;
in2='b01;
#10
in1='b11;
in2='b10;
#10
in1='b11;
in2='b11;


end

endmodule

doan2/arbiter/comparator/max_sel_tb.vcd
$date
	Mon Dec 20 17:32:03 2021
$end
$version
	Icarus Verilog
$end
$timescale
	1ns
$end
$scope module max_sel_tb $end
$var wire 1 ! sel $end
$var wire 2 " out [1:0] $end
$var reg 2 # in1 [1:0] $end
$var reg 2 $ in2 [1:0] $end
$scope module a $end
$var wire 2 % in1 [1:0] $end
$var wire 2 & in2 [1:0] $end
$var wire 1 ! sel $end
$var wire 2 ' out [1:0] $end
$upscope $end
$upscope $end
$enddefinitions $end
#0
$dumpvars
bx '
bx &
bx %
bx $
bx #
bx "
x!
$end
#10
0!
b0 "
b0 '
b0 $
b0 &
b0 #
b0 %
#20
b1 "
b1 '
b1 $
b1 &
#30
b10 "
b10 '
b10 $
b10 &
#40
b11 "
b11 '
b11 $
b11 &
#50
1!
b1 "
b1 '
b0 $
b0 &
b1 #
b1 %
#60
0!
b1 $
b1 &
#70
0!
b10 "
b10 '
b10 $
b10 &
#80
b11 "
b11 '
b11 $
b11 &
#90
1!
b10 "
b10 '
b0 $
b0 &
b10 #
b10 %
#100
b1 $
b1 &
#110
0!
b10 $
b10 &
#120
b11 "
b11 '
b11 $
b11 &
#130
1!
b11 "
b11 '
b0 $
b0 &
b11 #
b11 %
#140
b1 $
b1 &
#150
b10 $
b10 &
#160
0!
b11 $
b11 &
