uart/DUT_test/uart_rx.v
module uart_rx
(
    input             clk,reset,
    input             data_tx,
    output  [7:0]     data_out,
    output  [31:0]    address,
    output            we
);
parameter clk_rx=50000;
parameter Baudrate=10000;

parameter halfBaud=(clk_rx)/(Baudrate*2);

parameter address_rx='h400100;

reg     [7:0]      count;
reg                temp;

reg                idle;
reg     [3:0]      baud_counter;
reg     [8:0]      data_shift;
wire               restore;
wire               en;
wire               stop;
wire               switch;
wire               parity;


always @(posedge clk or posedge reset) begin
    if(reset) begin
        count<='b0;
        temp<='b0;
    end
    else begin
        if(en) count <= count + 1;
        if(count==halfBaud-1) begin
            temp=~temp;
            count<='b0;
        end
    end
end

assign restore=reset|stop;

always @(negedge data_tx or posedge restore) begin
    if(restore) idle <= 'b1;
    else begin
        /*if(stop) idle <= 'b1;
        else*/ idle <= 'b0;
    end
end

assign en=~idle;

always @(posedge temp or posedge reset) begin
    if(reset) baud_counter <= 'b0;
    else begin
        if(en&(!stop)) baud_counter <= baud_counter + 1;
    end
end

always @(posedge temp or posedge reset) begin
    if(reset) data_shift <='b0;
    else begin
        if(en) data_shift[8] <= data_tx;
        for(integer i = 0; i < 9; i=i+1) begin
            data_shift[i]=data_shift[i+1];
        end
    end
end

assign stop = baud_counter[3]&!baud_counter[2]&baud_counter[1]&!baud_counter[0];
assign parity = ^data_shift[7:0];

assign we=stop&!(data_shift[8]^parity);
assign data_out=data_shift[7:0];

assign address=address_rx;

endmodule

uart/DUT_test/uart_tx.v
module uart_tx
(
    input             clk,reset,en,
    input   [7:0]     data,
    output            data_tx,
    output            done
);
parameter clk_tx=50000;
parameter Baudrate=10000;

parameter halfBaud=(clk_tx)/(Baudrate*2);

reg     [7:0]      count;
reg                temp;

reg                idle;
reg     [3:0]      baud_counter;
reg     [7:0]      data_shift;
wire               stop;
wire               switch;
wire               parity;

always @(posedge clk or posedge reset) begin
    if(reset) begin
        count<='b0;
        temp<='b0;
    end
    else begin
        if(en) count <= count + 1;
        if(count==halfBaud-1) begin
            temp=~temp;
            count<='b0;
        end
    end
end

always @(posedge clk or posedge reset) begin
    if(reset) idle <= 'b1;
    else begin
        if(en) idle <= 'b0;
        if(stop) idle <= 'b1;
    end
end

always @(posedge temp or posedge reset) begin
    if(reset) baud_counter <= 'b0;
    else begin
        if(en&(!stop)) baud_counter <= baud_counter + 1;
    end
end

always @(posedge temp or posedge reset) begin
    if(reset) data_shift <='b0;
    else begin
        if(baud_counter == 'b1) data_shift <= data;
        //data_shift[7]='b0;
        for(integer i = 0; i < 7; i=i+1) begin
            data_shift[i]=data_shift[i+1];
        end
    end
end

assign stop = baud_counter[3]&!baud_counter[2]&baud_counter[1]&baud_counter[0];
assign switch = baud_counter[3]&!baud_counter[2]&baud_counter[1]&!baud_counter[0];
assign parity = ^data;

assign data_tx = idle|stop|(switch?parity:data_shift[0]);
assign done=stop;

endmodule

uart/uart.v
`include "uart_tx.v"
`include "uart_rx.v"

module uart
(
    input               clk,reset,en,
    input    [7:0]      data_in,
    output   [7:0]      data_out,
    output              done,we,
    output   [31:0]     address
);

wire    data;

uart_tx test0 ( .clk(clk), .reset(reset), .en(en),
                .data(data_in),
                .data_tx(data),
                .done(done));

uart_rx test1 ( .clk(clk), .reset(reset),
                .data_tx(data),
                .data_out(data_out),
                .we(we),
                .address(address));


endmodule

uart/DUT_test/DUT_code_for_TB.v
`include "uart.v"
`timescale 1ns/1ns

module DUT_code_for_TB
();

reg               clk,reset,en;
reg    [7:0]      data_in;
wire   [7:0]      data_out;
wire              done,we;
wire   [31:0]     address;

integer file_input;
integer file_output;

uart test( .clk(clk), .reset(reset), .en(en),
           .data_in(data_in),
           .data_out(data_out),
           .done(done), .we(we),
           .address(address));
			  


initial begin
file_input = $fopen("input.txt","w");
file_output = $fopen("output.txt","w");
$dumpfile("DUT_code_for_TB.vcd");
$dumpvars(0,DUT_code_for_TB);
clk='b0;
reset='b1;
en='b0;
data_in='h00;
#10
clk=~clk;
reset=~reset;
repeat(1)#10 clk=~clk;
en=~en;
repeat (22526)#10 clk=~clk;
$fclose(file_input);
$fclose(file_output);
end
//DUT testing
always @(clk) begin
		if ((done == 1) && (data_in <= 8'hff))begin
			$fdisplayb(file_input,data_in);
			$fdisplayb(file_output,data_out);
			//$fdisplay(file_input,"value display with $fstrobe");
			data_in <= data_in + 1;
		   #10 en <= 1;
			#10 reset <= 1;
			#10 reset <= 0;
			end
		
		$display("done");
end



endmodule

uart/DUT_test/DUT_code_for_TB.vcd
$date
	Sat Jan  8 11:31:14 2022
$end
$version
	Icarus Verilog
$end
$timescale
	1ns
$end
$scope module DUT_code_for_TB $end
$var wire 32 ! address [31:0] $end
$var wire 1 " we $end
$var wire 1 # done $end
$var wire 8 $ data_out [7:0] $end
$var reg 1 % clk $end
$var reg 8 & data_in [7:0] $end
$var reg 1 ' en $end
$var reg 1 ( reset $end
$var integer 32 ) file_input [31:0] $end
$var integer 32 * file_output [31:0] $end
$scope module test $end
$var wire 32 + address [31:0] $end
$var wire 1 % clk $end
$var wire 8 , data_in [7:0] $end
$var wire 1 ' en $end
$var wire 1 ( reset $end
$var wire 1 " we $end
$var wire 1 # done $end
$var wire 8 - data_out [7:0] $end
$var wire 1 . data $end
$scope module test0 $end
$var wire 1 % clk $end
$var wire 8 / data [7:0] $end
$var wire 1 . data_tx $end
$var wire 1 # done $end
$var wire 1 ' en $end
$var wire 1 ( reset $end
$var wire 1 0 stop $end
$var wire 1 1 switch $end
$var wire 1 2 parity $end
$var reg 4 3 baud_counter [3:0] $end
$var reg 8 4 count [7:0] $end
$var reg 8 5 data_shift [7:0] $end
$var reg 1 6 idle $end
$var reg 1 7 temp $end
$scope begin $ivl_for_loop0 $end
$var integer 32 8 i [31:0] $end
$upscope $end
$upscope $end
$scope module test1 $end
$var wire 32 9 address [31:0] $end
$var wire 1 % clk $end
$var wire 1 . data_tx $end
$var wire 1 : en $end
$var wire 1 ( reset $end
$var wire 1 ; restore $end
$var wire 1 < stop $end
$var wire 1 " we $end
$var wire 1 = parity $end
$var wire 8 > data_out [7:0] $end
$var reg 4 ? baud_counter [3:0] $end
$var reg 8 @ count [7:0] $end
$var reg 9 A data_shift [8:0] $end
$var reg 1 B idle $end
$var reg 1 C temp $end
$scope begin $ivl_for_loop1 $end
$var integer 32 D i [31:0] $end
$upscope $end
$upscope $end
$upscope $end
$upscope $end
$enddefinitions $end
#0
$dumpvars
bx D
0C
1B
b0 A
b0 @
b0 ?
b0 >
0=
0<
1;
0:
b10000000000000100000000 9
bx 8
07
16
b0 5
b0 4
b0 3
02
01
00
b0 /
1.
b0 -
b0 ,
b10000000000000100000000 +
b10000000000000000000000000000100 *
b10000000000000000000000000000011 )
1(
0'
b0 &
0%
b0 $
0#
0"
b10000000000000100000000 !
$end
#10
0;
0(
1%
#20
1'
0%
#30
1:
0B
0.
b1 4
06
1%
#40
0%
#50
b1 3
b1 @
b0 4
b111 8
17
1%
#60
0%
#70
b1 ?
b1 4
b0 @
b0 A
b1001 D
1C
1%
#80
0%
#90
b1 @
b0 4
07
1%
#100
0%
#110
b1 4
b0 @
0C
1%
#120
0%
#130
b10 3
b1 @
b0 4
b111 8
17
1%
#140
0%
#150
b10 ?
b1 4
b0 @
b0 A
b1001 D
1C
1%
#160
0%
#170
b1 @
b0 4
07
1%
#180
0%
#190
b1 4
b0 @
0C
1%
#200
0%
#210
b11 3
b1 @
b0 4
b111 8
17
1%
#220
0%
#230
b11 ?
b1 4
b0 @
b0 A
b1001 D
1C
1%
#240
0%
#250
b1 @
b0 4
07
1%
#260
0%
#270
b1 4
b0 @
0C
1%
#280
0%
#290
b100 3
b1 @
b0 4
b111 8
17
1%
#300
0%
#310
b100 ?
b1 4
b0 @
b0 A
b1001 D
1C
1%
#320
0%
#330
b1 @
b0 4
07
1%
#340
0%
#350
b1 4
b0 @
0C
1%
#360
0%
#370
b101 3
b1 @
b0 4
b111 8
17
1%
#380
0%
#390
b101 ?
b1 4
b0 @
b0 A
b1001 D
1C
1%
#400
0%
#410
b1 @
b0 4
07
1%
#420
0%
#430
b1 4
b0 @
0C
1%
#440
0%
#450
b110 3
b1 @
b0 4
b111 8
17
1%
#460
0%
#470
b110 ?
b1 4
b0 @
b0 A
b1001 D
1C
1%
#480
0%
#490
b1 @
b0 4
07
1%
#500
0%
#510
b1 4
b0 @
0C
1%
#520
0%
#530
b111 3
b1 @
b0 4
b111 8
17
1%
#540
0%
#550
b111 ?
b1 4
b0 @
b0 A
b1001 D
1C
1%
#560
0%
#570
b1 @
b0 4
07
1%
#580
0%
#590
b1 4
b0 @
0C
1%
#600
0%
#610
b1000 3
b1 @
b0 4
b111 8
17
1%
#620
0%
#630
b1000 ?
b1 4
b0 @
b0 A
b1001 D
1C
1%
#640
0%
#650
b1 @
b0 4
07
1%
#660
0%
#670
b1 4
b0 @
0C
1%
#680
0%
#690
b1001 3
b1 @
b0 4
b111 8
17
1%
#700
0%
#710
b1001 ?
b1 4
b0 @
b0 A
b1001 D
1C
1%
#720
0%
#730
b1 @
b0 4
07
1%
#740
0%
#750
b1 4
b0 @
0C
1%
#760
0%
#770
11
b1010 3
b1 @
b0 4
b111 8
17
1%
#780
0%
#790
0:
1B
1;
1<
b1010 ?
b1 4
b0 @
b0 A
b1001 D
1C
1%
#800
0%
#810
b0 4
07
1%
#820
0%
#830
b1 4
1%
#840
0%
#850
1.
1#
10
01
b1011 3
b0 4
b111 8
17
1%
#860
12
b1 &
b1 ,
b1 /
0%
#870
b1 4
16
1%
#880
0<
0#
00
01
b0 3
0C
07
b0 4
b0 ?
1(
0%
#890
0;
0(
1%
#900
0%
#910
1:
0B
0.
06
b1 4
1%
#920
0%
#930
b1 3
b0 4
b1 @
b111 8
17
1%
#940
0%
#950
b1 ?
b0 @
b1 4
b0 A
b1001 D
1C
1%
#960
0%
#970
b0 4
b1 @
07
1%
#980
0%
#990
b0 @
b1 4
0C
1%
#1000
0%
#1010
1.
b10 3
b1 5
b0 4
b1 @
b111 8
17
1%
#1020
0%
#1030
b10 ?
b0 @
b1 4
b100000000 A
b1001 D
1C
1%
#1040
0%
#1050
b0 4
b1 @
07
1%
#1060
0%
#1070
b0 @
b1 4
0C
1%
#1080
0%
#1090
b11 3
b0 4
b1 @
0.
b0 5
b111 8
17
1%
#1100
0%
#1110
b11 ?
b0 @
b1 4
1=
b10000000 $
b10000000 -
b10000000 >
b10000000 A
b1001 D
1C
1%
#1120
0%
#1130
b0 4
b1 @
07
1%
#1140
0%
#1150
b0 @
b1 4
0C
1%
#1160
0%
#1170
b100 3
b0 4
b1 @
b111 8
17
1%
#1180
0%
#1190
b100 ?
b0 @
b1 4
b1000000 $
b1000000 -
b1000000 >
b1000000 A
b1001 D
1C
1%
#1200
0%
#1210
b0 4
b1 @
07
1%
#1220
0%
#1230
b0 @
b1 4
0C
1%
#1240
0%
#1250
b101 3
b0 4
b1 @
b111 8
17
1%
#1260
0%
#1270
b101 ?
b0 @
b1 4
b100000 $
b100000 -
b100000 >
b100000 A
b1001 D
1C
1%
#1280
0%
#1290
b0 4
b1 @
07
1%
#1300
0%
#1310
b0 @
b1 4
0C
1%
#1320
0%
#1330
b110 3
b0 4
b1 @
b111 8
17
1%
#1340
0%
#1350
b110 ?
b0 @
b1 4
b10000 $
b10000 -
b10000 >
b10000 A
b1001 D
1C
1%
#1360
0%
#1370
b0 4
b1 @
07
1%
#1380
0%
#1390
b0 @
b1 4
0C
1%
#1400
0%
#1410
b111 3
b0 4
b1 @
b111 8
17
1%
#1420
0%
#1430
b111 ?
b0 @
b1 4
b1000 $
b1000 -
b1000 >
b1000 A
b1001 D
1C
1%
#1440
0%
#1450
b0 4
b1 @
07
1%
#1460
0%
#1470
b0 @
b1 4
0C
1%
#1480
0%
#1490
b1000 3
b0 4
b1 @
b111 8
17
1%
#1500
0%
#1510
b1000 ?
b0 @
b1 4
b100 $
b100 -
b100 >
b100 A
b1001 D
1C
1%
#1520
0%
#1530
b0 4
b1 @
07
1%
#1540
0%
#1550
b0 @
b1 4
0C
1%
#1560
0%
#1570
b1001 3
b0 4
b1 @
b111 8
17
1%
#1580
0%
#1590
b1001 ?
b0 @
b1 4
b10 $
b10 -
b10 >
b10 A
b1001 D
1C
1%
#1600
0%
#1610
b0 4
b1 @
07
1%
#1620
0%
#1630
b0 @
b1 4
0C
1%
#1640
0%
#1650
1.
11
b1010 3
b0 4
b1 @
b111 8
17
1%
#1660
0%
#1670
0:
1B
1"
1;
1<
b1010 ?
b0 @
b1 4
b1 $
b1 -
b1 >
b100000001 A
b1001 D
1C
1%
#1680
0%
#1690
b0 4
07
1%
#1700
0%
#1710
b1 4
1%
#1720
0%
#1730
1#
10
01
b1011 3
b0 4
b111 8
17
1%
#1740
b10 &
b10 ,
b10 /
0%
#1750
16
b1 4
1%
#1760
0<
0"
0#
00
01
0=
b0 $
b0 -
b0 >
b0 3
07
b0 4
0C
b0 ?
b0 A
1(
0%
#1770
0;
0(
1%
#1780
0%
#1790
1:
0B
0.
b1 4
06
1%
#1800
0%
#1810
b1 3
b1 @
b0 4
b111 8
17
1%
#1820
0%
#1830
b1 ?
b1 4
b0 @
b0 A
b1001 D
1C
1%
#1840
0%
#1850
b1 @
b0 4
07
1%
#1860
0%
#1870
b1 4
b0 @
0C
1%
#1880
0%
#1890
b10 3
b10 5
b1 @
b0 4
b111 8
17
1%
#1900
0%
#1910
b10 ?
b1 4
b0 @
b0 A
b1001 D
1C
1%
#1920
0%
#1930
b1 @
b0 4
07
1%
#1940
0%
#1950
b1 4
b0 @
0C
1%
#1960
0%
#1970
b11 3
b1 @
b0 4
1.
b1 5
b111 8
17
1%
#1980
0%
#1990
b11 ?
b1 4
b0 @
b100000000 A
b1001 D
1C
1%
#2000
0%
#2010
b1 @
b0 4
07
1%
#2020
0%
#2030
b1 4
b0 @
0C
1%
#2040
0%
#2050
b100 3
b1 @
b0 4
0.
b0 5
b111 8
17
1%
#2060
0%
#2070
b100 ?
b1 4
b0 @
1=
b10000000 $
b10000000 -
b10000000 >
b10000000 A
b1001 D
1C
1%
#2080
0%
#2090
b1 @
b0 4
07
1%
#2100
0%
#2110
b1 4
b0 @
0C
1%
#2120
0%
#2130
b101 3
b1 @
b0 4
b111 8
17
1%
#2140
0%
#2150
b101 ?
b1 4
b0 @
b1000000 $
b1000000 -
b1000000 >
b1000000 A
b1001 D
1C
1%
#2160
0%
#2170
b1 @
b0 4
07
1%
#2180
0%
#2190
b1 4
b0 @
0C
1%
#2200
0%
#2210
b110 3
b1 @
b0 4
b111 8
17
1%
#2220
0%
#2230
b110 ?
b1 4
b0 @
b100000 $
b100000 -
b100000 >
b100000 A
b1001 D
1C
1%
#2240
0%
#2250
b1 @
b0 4
07
1%
#2260
0%
#2270
b1 4
b0 @
0C
1%
#2280
0%
#2290
b111 3
b1 @
b0 4
b111 8
17
1%
#2300
0%
#2310
b111 ?
b1 4
b0 @
b10000 $
b10000 -
b10000 >
b10000 A
b1001 D
1C
1%
#2320
0%
#2330
b1 @
b0 4
07
1%
#2340
0%
#2350
b1 4
b0 @
0C
1%
#2360
0%
#2370
b1000 3
b1 @
b0 4
b111 8
17
1%
#2380
0%
#2390
b1000 ?
b1 4
b0 @
b1000 $
b1000 -
b1000 >
b1000 A
b1001 D
1C
1%
#2400
0%
#2410
b1 @
b0 4
07
1%
#2420
0%
#2430
b1 4
b0 @
0C
1%
#2440
0%
#2450
b1001 3
b1 @
b0 4
b111 8
17
1%
#2460
0%
#2470
b1001 ?
b1 4
b0 @
b100 $
b100 -
b100 >
b100 A
b1001 D
1C
1%
#2480
0%
#2490
b1 @
b0 4
07
1%
#2500
0%
#2510
b1 4
b0 @
0C
1%
#2520
0%
#2530
1.
11
b1010 3
b1 @
b0 4
b111 8
17
1%
#2540
0%
#2550
0:
1B
1"
1;
1<
b1010 ?
b1 4
b0 @
b10 $
b10 -
b10 >
b100000010 A
b1001 D
1C
1%
#2560
0%
#2570
b0 4
07
1%
#2580
0%
#2590
b1 4
1%
#2600
0%
#2610
1#
10
01
b1011 3
b0 4
b111 8
17
1%
#2620
02
b11 &
b11 ,
b11 /
0%
#2630
b1 4
16
1%
#2640
0<
0"
0#
00
01
0=
b0 $
b0 -
b0 >
b0 3
0C
07
b0 4
b0 ?
b0 A
1(
0%
#2650
0;
0(
1%
#2660
0%
#2670
1:
0B
0.
06
b1 4
1%
#2680
0%
#2690
b1 3
b0 4
b1 @
b111 8
17
1%
#2700
0%
#2710
b1 ?
b0 @
b1 4
b0 A
b1001 D
1C
1%
#2720
0%
#2730
b0 4
b1 @
07
1%
#2740
0%
#2750
b0 @
b1 4
0C
1%
#2760
0%
#2770
1.
b10 3
b11 5
b0 4
b1 @
b111 8
17
1%
#2780
0%
#2790
b10 ?
b0 @
b1 4
b100000000 A
b1001 D
1C
1%
#2800
0%
#2810
b0 4
b1 @
07
1%
#2820
0%
#2830
b0 @
b1 4
0C
1%
#2840
0%
#2850
b11 3
b0 4
b1 @
b1 5
b111 8
17
1%
#2860
0%
#2870
b11 ?
b0 @
b1 4
1=
b10000000 $
b10000000 -
b10000000 >
b110000000 A
b1001 D
1C
1%
#2880
0%
#2890
b0 4
b1 @
07
1%
#2900
0%
#2910
b0 @
b1 4
0C
1%
#2920
0%
#2930
b100 3
b0 4
b1 @
0.
b0 5
b111 8
17
1%
#2940
0%
#2950
b100 ?
b0 @
b1 4
0=
b11000000 $
b11000000 -
b11000000 >
b11000000 A
b1001 D
1C
1%
#2960
0%
#2970
b0 4
b1 @
07
1%
#2980
0%
#2990
b0 @
b1 4
0C
1%
#3000
0%
#3010
b101 3
b0 4
b1 @
b111 8
17
1%
#3020
0%
#3030
b101 ?
b0 @
b1 4
b1100000 $
b1100000 -
b1100000 >
b1100000 A
b1001 D
1C
1%
#3040
0%
#3050
b0 4
b1 @
07
1%
#3060
0%
#3070
b0 @
b1 4
0C
1%
#3080
0%
#3090
b110 3
b0 4
b1 @
b111 8
17
1%
#3100
0%
#3110
b110 ?
b0 @
b1 4
b110000 $
b110000 -
b110000 >
b110000 A
b1001 D
1C
1%
#3120
0%
#3130
b0 4
b1 @
07
1%
#3140
0%
#3150
b0 @
b1 4
0C
1%
#3160
0%
#3170
b111 3
b0 4
b1 @
b111 8
17
1%
#3180
0%
#3190
b111 ?
b0 @
b1 4
b11000 $
b11000 -
b11000 >
b11000 A
b1001 D
1C
1%
#3200
0%
#3210
b0 4
b1 @
07
1%
#3220
0%
#3230
b0 @
b1 4
0C
1%
#3240
0%
#3250
b1000 3
b0 4
b1 @
b111 8
17
1%
#3260
0%
#3270
b1000 ?
b0 @
b1 4
b1100 $
b1100 -
b1100 >
b1100 A
b1001 D
1C
1%
#3280
0%
#3290
b0 4
b1 @
07
1%
#3300
0%
#3310
b0 @
b1 4
0C
1%
#3320
0%
#3330
b1001 3
b0 4
b1 @
b111 8
17
1%
#3340
0%
#3350
b1001 ?
b0 @
b1 4
b110 $
b110 -
b110 >
b110 A
b1001 D
1C
1%
#3360
0%
#3370
b0 4
b1 @
07
1%
#3380
0%
#3390
b0 @
b1 4
0C
1%
#3400
0%
#3410
11
b1010 3
b0 4
b1 @
b111 8
17
1%
#3420
0%
#3430
0:
1B
1;
1<
b1010 ?
b0 @
b1 4
b11 $
b11 -
b11 >
b11 A
b1001 D
1C
1%
#3440
0%
#3450
b0 4
07
1%
#3460
0%
#3470
b1 4
1%
#3480
0%
#3490
1.
1#
10
01
b1011 3
b0 4
b111 8
17
1%
#3500
12
b100 &
b100 ,
b100 /
0%
#3510
16
b1 4
1%
#3520
0<
0#
00
01
b0 $
b0 -
b0 >
b0 3
07
b0 4
0C
b0 ?
b0 A
1(
0%
#3530
0;
0(
1%
#3540
0%
#3550
1:
0B
0.
b1 4
06
1%
#3560
0%
#3570
b1 3
b1 @
b0 4
b111 8
17
1%
#3580
0%
#3590
b1 ?
b1 4
b0 @
b0 A
b1001 D
1C
1%
#3600
0%
#3610
b1 @
b0 4
07
1%
#3620
0%
#3630
b1 4
b0 @
0C
1%
#3640
0%
#3650
b10 3
b100 5
b1 @
b0 4
b111 8
17
1%
#3660
0%
#3670
b10 ?
b1 4
b0 @
b0 A
b1001 D
1C
1%
#3680
0%
#3690
b1 @
b0 4
07
1%
#3700
0%
#3710
b1 4
b0 @
0C
1%
#3720
0%
#3730
b11 3
b1 @
b0 4
b10 5
b111 8
17
1%
#3740
0%
#3750
b11 ?
b1 4
b0 @
b0 A
b1001 D
1C
1%
#3760
0%
#3770
b1 @
b0 4
07
1%
#3780
0%
#3790
b1 4
b0 @
0C
1%
#3800
0%
#3810
b100 3
b1 @
b0 4
1.
b1 5
b111 8
17
1%
#3820
0%
#3830
b100 ?
b1 4
b0 @
b100000000 A
b1001 D
1C
1%
#3840
0%
#3850
b1 @
b0 4
07
1%
#3860
0%
#3870
b1 4
b0 @
0C
1%
#3880
0%
#3890
b101 3
b1 @
b0 4
0.
b0 5
b111 8
17
1%
#3900
0%
#3910
b101 ?
b1 4
b0 @
1=
b10000000 $
b10000000 -
b10000000 >
b10000000 A
b1001 D
1C
1%
#3920
0%
#3930
b1 @
b0 4
07
1%
#3940
0%
#3950
b1 4
b0 @
0C
1%
#3960
0%
#3970
b110 3
b1 @
b0 4
b111 8
17
1%
#3980
0%
#3990
b110 ?
b1 4
b0 @
b1000000 $
b1000000 -
b1000000 >
b1000000 A
b1001 D
1C
1%
#4000
0%
#4010
b1 @
b0 4
07
1%
#4020
0%
#4030
b1 4
b0 @
0C
1%
#4040
0%
#4050
b111 3
b1 @
b0 4
b111 8
17
1%
#4060
0%
#4070
b111 ?
b1 4
b0 @
b100000 $
b100000 -
b100000 >
b100000 A
b1001 D
1C
1%
#4080
0%
#4090
b1 @
b0 4
07
1%
#4100
0%
#4110
b1 4
b0 @
0C
1%
#4120
0%
#4130
b1000 3
b1 @
b0 4
b111 8
17
1%
#4140
0%
#4150
b1000 ?
b1 4
b0 @
b10000 $
b10000 -
b10000 >
b10000 A
b1001 D
1C
1%
#4160
0%
#4170
b1 @
b0 4
07
1%
#4180
0%
#4190
b1 4
b0 @
0C
1%
#4200
0%
#4210
b1001 3
b1 @
b0 4
b111 8
17
1%
#4220
0%
#4230
b1001 ?
b1 4
b0 @
b1000 $
b1000 -
b1000 >
b1000 A
b1001 D
1C
1%
#4240
0%
#4250
b1 @
b0 4
07
1%
#4260
0%
#4270
b1 4
b0 @
0C
1%
#4280
0%
#4290
1.
11
b1010 3
b1 @
b0 4
b111 8
17
1%
#4300
0%
#4310
0:
1B
1"
1;
1<
b1010 ?
b1 4
b0 @
b100 $
b100 -
b100 >
b100000100 A
b1001 D
1C
1%
#4320
0%
#4330
b0 4
07
1%
#4340
0%
#4350
b1 4
1%
#4360
0%
#4370
1#
10
01
b1011 3
b0 4
b111 8
17
1%
#4380
02
b101 &
b101 ,
b101 /
0%
#4390
b1 4
16
1%
#4400
0<
0"
0#
00
01
0=
b0 $
b0 -
b0 >
b0 3
0C
07
b0 4
b0 ?
b0 A
1(
0%
#4410
0;
0(
1%
#4420
0%
#4430
1:
0B
0.
06
b1 4
1%
#4440
0%
#4450
b1 3
b0 4
b1 @
b111 8
17
1%
#4460
0%
#4470
b1 ?
b0 @
b1 4
b0 A
b1001 D
1C
1%
#4480
0%
#4490
b0 4
b1 @
07
1%
#4500
0%
#4510
b0 @
b1 4
0C
1%
#4520
0%
#4530
1.
b10 3
b101 5
b0 4
b1 @
b111 8
17
1%
#4540
0%
#4550
b10 ?
b0 @
b1 4
b100000000 A
b1001 D
1C
1%
#4560
0%
#4570
b0 4
b1 @
07
1%
#4580
0%
#4590
b0 @
b1 4
0C
1%
#4600
0%
#4610
b11 3
b0 4
b1 @
0.
b10 5
b111 8
17
1%
#4620
0%
#4630
b11 ?
b0 @
b1 4
1=
b10000000 $
b10000000 -
b10000000 >
b10000000 A
b1001 D
1C
1%
#4640
0%
#4650
b0 4
b1 @
07
1%
#4660
0%
#4670
b0 @
b1 4
0C
1%
#4680
0%
#4690
b100 3
b0 4
b1 @
1.
b1 5
b111 8
17
1%
#4700
0%
#4710
b100 ?
b0 @
b1 4
b1000000 $
b1000000 -
b1000000 >
b101000000 A
b1001 D
1C
1%
#4720
0%
#4730
b0 4
b1 @
07
1%
#4740
0%
#4750
b0 @
b1 4
0C
1%
#4760
0%
#4770
b101 3
b0 4
b1 @
0.
b0 5
b111 8
17
1%
#4780
0%
#4790
b101 ?
b0 @
b1 4
0=
b10100000 $
b10100000 -
b10100000 >
b10100000 A
b1001 D
1C
1%
#4800
0%
#4810
b0 4
b1 @
07
1%
#4820
0%
#4830
b0 @
b1 4
0C
1%
#4840
0%
#4850
b110 3
b0 4
b1 @
b111 8
17
1%
#4860
0%
#4870
b110 ?
b0 @
b1 4
b1010000 $
b1010000 -
b1010000 >
b1010000 A
b1001 D
1C
1%
#4880
0%
#4890
b0 4
b1 @
07
1%
#4900
0%
#4910
b0 @
b1 4
0C
1%
#4920
0%
#4930
b111 3
b0 4
b1 @
b111 8
17
1%
#4940
0%
#4950
b111 ?
b0 @
b1 4
b101000 $
b101000 -
b101000 >
b101000 A
b1001 D
1C
1%
#4960
0%
#4970
b0 4
b1 @
07
1%
#4980
0%
#4990
b0 @
b1 4
0C
1%
#5000
0%
#5010
b1000 3
b0 4
b1 @
b111 8
17
1%
#5020
0%
#5030
b1000 ?
b0 @
b1 4
b10100 $
b10100 -
b10100 >
b10100 A
b1001 D
1C
1%
#5040
0%
#5050
b0 4
b1 @
07
1%
#5060
0%
#5070
b0 @
b1 4
0C
1%
#5080
0%
#5090
b1001 3
b0 4
b1 @
b111 8
17
1%
#5100
0%
#5110
b1001 ?
b0 @
b1 4
b1010 $
b1010 -
b1010 >
b1010 A
b1001 D
1C
1%
#5120
0%
#5130
b0 4
b1 @
07
1%
#5140
0%
#5150
b0 @
b1 4
0C
1%
#5160
0%
#5170
11
b1010 3
b0 4
b1 @
b111 8
17
1%
#5180
0%
#5190
0:
1B
1;
1<
b1010 ?
b0 @
b1 4
b101 $
b101 -
b101 >
b101 A
b1001 D
1C
1%
#5200
0%
#5210
b0 4
07
1%
#5220
0%
#5230
b1 4
1%
#5240
0%
#5250
1.
1#
10
01
b1011 3
b0 4
b111 8
17
1%
#5260
b110 &
b110 ,
b110 /
0%
#5270
16
b1 4
1%
#5280
0<
0#
00
01
b0 $
b0 -
b0 >
b0 3
07
b0 4
0C
b0 ?
b0 A
1(
0%
#5290
0;
0(
1%
#5300
0%
#5310
1:
0B
0.
b1 4
06
1%
#5320
0%
#5330
b1 3
b1 @
b0 4
b111 8
17
1%
#5340
0%
#5350
b1 ?
b1 4
b0 @
b0 A
b1001 D
1C
1%
#5360
0%
#5370
b1 @
b0 4
07
1%
#5380
0%
#5390
b1 4
b0 @
0C
1%
#5400
0%
#5410
b10 3
b110 5
b1 @
b0 4
b111 8
17
1%
#5420
0%
#5430
b10 ?
b1 4
b0 @
b0 A
b1001 D
1C
1%
#5440
0%
#5450
b1 @
b0 4
07
1%
#5460
0%
#5470
b1 4
b0 @
0C
1%
#5480
0%
#5490
b11 3
b1 @
b0 4
1.
b11 5
b111 8
17
1%
#5500
0%
#5510
b11 ?
b1 4
b0 @
b100000000 A
b1001 D
1C
1%
#5520
0%
#5530
b1 @
b0 4
07
1%
#5540
0%
#5550
b1 4
b0 @
0C
1%
#5560
0%
#5570
b100 3
b1 @
b0 4
b1 5
b111 8
17
1%
#5580
0%
#5590
b100 ?
b1 4
b0 @
1=
b10000000 $
b10000000 -
b10000000 >
b110000000 A
b1001 D
1C
1%
#5600
0%
#5610
b1 @
b0 4
07
1%
#5620
0%
#5630
b1 4
b0 @
0C
1%
#5640
0%
#5650
b101 3
b1 @
b0 4
0.
b0 5
b111 8
17
1%
#5660
0%
#5670
b101 ?
b1 4
b0 @
0=
b11000000 $
b11000000 -
b11000000 >
b11000000 A
b1001 D
1C
1%
#5680
0%
#5690
b1 @
b0 4
07
1%
#5700
0%
#5710
b1 4
b0 @
0C
1%
#5720
0%
#5730
b110 3
b1 @
b0 4
b111 8
17
1%
#5740
0%
#5750
b110 ?
b1 4
b0 @
b1100000 $
b1100000 -
b1100000 >
b1100000 A
b1001 D
1C
1%
#5760
0%
#5770
b1 @
b0 4
07
1%
#5780
0%
#5790
b1 4
b0 @
0C
1%
#5800
0%
#5810
b111 3
b1 @
b0 4
b111 8
17
1%
#5820
0%
#5830
b111 ?
b1 4
b0 @
b110000 $
b110000 -
b110000 >
b110000 A
b1001 D
1C
1%
#5840
0%
#5850
b1 @
b0 4
07
1%
#5860
0%
#5870
b1 4
b0 @
0C
1%
#5880
0%
#5890
b1000 3
b1 @
b0 4
b111 8
17
1%
#5900
0%
#5910
b1000 ?
b1 4
b0 @
b11000 $
b11000 -
b11000 >
b11000 A
b1001 D
1C
1%
#5920
0%
#5930
b1 @
b0 4
07
1%
#5940
0%
#5950
b1 4
b0 @
0C
1%
#5960
0%
#5970
b1001 3
b1 @
b0 4
b111 8
17
1%
#5980
0%
#5990
b1001 ?
b1 4
b0 @
b1100 $
b1100 -
b1100 >
b1100 A
b1001 D
1C
1%
#6000
0%
#6010
b1 @
b0 4
07
1%
#6020
0%
#6030
b1 4
b0 @
0C
1%
#6040
0%
#6050
11
b1010 3
b1 @
b0 4
b111 8
17
1%
#6060
0%
#6070
0:
1B
1;
1<
b1010 ?
b1 4
b0 @
b110 $
b110 -
b110 >
b110 A
b1001 D
1C
1%
#6080
0%
#6090
b0 4
07
1%
#6100
0%
#6110
b1 4
1%
#6120
0%
#6130
1.
1#
10
01
b1011 3
b0 4
b111 8
17
1%
#6140
12
b111 &
b111 ,
b111 /
0%
#6150
b1 4
16
1%
