uart/DUT_test/uart_tx.v
module uart_tx
(
    input             clk,reset,en,
    input   [7:0]     data,
    output            data_tx,
    output            done
);
parameter clk_tx=50000;
parameter Baudrate=10000;

parameter halfBaud=(clk_tx)/(Baudrate*2);

reg     [7:0]      count;
reg                temp;

reg                idle;
reg     [3:0]      baud_counter;
reg     [7:0]      data_shift;
wire               stop;
wire               switch;
wire               parity;

always @(posedge clk or posedge reset) begin
    if(reset) begin
        count<='b0;
        temp<='b0;
    end
    else begin
        if(en) count <= count + 1;
        if(count==halfBaud-1) begin
            temp=~temp;
            count<='b0;
        end
    end
end

always @(posedge clk or posedge reset) begin
    if(reset) idle <= 'b1;
    else begin
        if(en) idle <= 'b0;
        if(stop) idle <= 'b1;
    end
end

always @(posedge temp or posedge reset) begin
    if(reset) baud_counter <= 'b0;
    else begin
        if(en&(!stop)) baud_counter <= baud_counter + 1;
    end
end

always @(posedge temp or posedge reset) begin
    if(reset) data_shift <='b0;
    else begin
        if(baud_counter == 'b1) data_shift <= data;
        //data_shift[7]='b0;
        for(integer i = 0; i < 7; i=i+1) begin
            data_shift[i]=data_shift[i+1];
        end
    end
end

assign stop = baud_counter[3]&!baud_counter[2]&baud_counter[1]&baud_counter[0];
assign switch = baud_counter[3]&!baud_counter[2]&baud_counter[1]&!baud_counter[0];
assign parity = ^data;

assign data_tx = idle|stop|(switch?parity:data_shift[0]);
assign done=stop;

endmodule

uart/uart_tx/uart_tx_tb.v
`include "uart_tx.v"
`timescale 1ns/1ns

module uart_tx_tb
();

reg             clk,reset,en;
reg   [7:0]     data;
wire            data_tx;

uart_tx test_tx( .clk(clk), .reset(reset), .en(en),
                 .data(data),
                 .data_tx(data_tx));



initial begin
$dumpfile("uart_tx_tb.vcd");
$dumpvars(0,uart_tx_tb);
clk='b0;
reset='b1;
en='b0;
data='b01110110;
#10
clk=~clk;
reset=~reset;
repeat(2)#10 clk=~clk;
en=~en;
repeat (100)#10 clk=~clk;


end

endmodule

uart/uart_tx/uart_tx_tb.vcd
$date
	Thu Jan  6 16:53:44 2022
$end
$version
	Icarus Verilog
$end
$timescale
	1ns
$end
$scope module uart_tx_tb $end
$var wire 1 ! data_tx $end
$var reg 1 " clk $end
$var reg 8 # data [7:0] $end
$var reg 1 $ en $end
$var reg 1 % reset $end
$scope module test_tx $end
$var wire 1 " clk $end
$var wire 8 & data [7:0] $end
$var wire 1 ! data_tx $end
$var wire 1 ' done $end
$var wire 1 $ en $end
$var wire 1 % reset $end
$var wire 1 ( stop $end
$var wire 1 ) switch $end
$var wire 1 * parity $end
$var reg 4 + baud_counter [3:0] $end
$var reg 8 , count [7:0] $end
$var reg 8 - data_shift [7:0] $end
$var reg 1 . idle $end
$var reg 1 / temp $end
$scope begin $ivl_for_loop0 $end
$var integer 32 0 i [31:0] $end
$upscope $end
$upscope $end
$upscope $end
$enddefinitions $end
#0
$dumpvars
bx 0
0/
1.
b0 -
b0 ,
b0 +
1*
0)
0(
0'
b1110110 &
1%
0$
b1110110 #
0"
1!
$end
#10
0%
1"
#20
0"
#30
0!
b1 ,
0.
1$
1"
#40
0"
#50
b1 +
b0 ,
b111 0
1/
1"
#60
0"
#70
b1 ,
1"
#80
0"
#90
b0 ,
0/
1"
#100
0"
#110
b1 ,
1"
#120
0"
#130
b10 +
b1110110 -
b0 ,
b111 0
1/
1"
#140
0"
#150
b1 ,
1"
#160
0"
#170
b0 ,
0/
1"
#180
0"
#190
b1 ,
1"
#200
0"
#210
b11 +
b0 ,
1!
b111011 -
b111 0
1/
1"
#220
0"
#230
b1 ,
1"
#240
0"
#250
b0 ,
0/
1"
#260
0"
#270
b1 ,
1"
#280
0"
#290
b100 +
b0 ,
b11101 -
b111 0
1/
1"
#300
0"
#310
b1 ,
1"
#320
0"
#330
b0 ,
0/
1"
#340
0"
#350
b1 ,
1"
#360
0"
#370
b101 +
b0 ,
0!
b1110 -
b111 0
1/
1"
#380
0"
#390
b1 ,
1"
#400
0"
#410
b0 ,
0/
1"
#420
0"
#430
b1 ,
1"
#440
0"
#450
b110 +
b0 ,
1!
b111 -
b111 0
1/
1"
#460
0"
#470
b1 ,
1"
#480
0"
#490
b0 ,
0/
1"
#500
0"
#510
b1 ,
1"
#520
0"
#530
b111 +
b0 ,
b11 -
b111 0
1/
1"
#540
0"
#550
b1 ,
1"
#560
0"
#570
b0 ,
0/
1"
#580
0"
#590
b1 ,
1"
#600
0"
#610
b1000 +
b0 ,
b1 -
b111 0
1/
1"
#620
0"
#630
b1 ,
1"
#640
0"
#650
b0 ,
0/
1"
#660
0"
#670
b1 ,
1"
#680
0"
#690
b1001 +
b0 ,
0!
b0 -
b111 0
1/
1"
#700
0"
#710
b1 ,
1"
#720
0"
#730
b0 ,
0/
1"
#740
0"
#750
b1 ,
1"
#760
0"
#770
1!
1)
b1010 +
b0 ,
b111 0
1/
1"
#780
0"
#790
b1 ,
1"
#800
0"
#810
b0 ,
0/
1"
#820
0"
#830
b1 ,
1"
#840
0"
#850
1'
1(
0)
b1011 +
b0 ,
b111 0
1/
1"
#860
0"
#870
b1 ,
1.
1"
#880
0"
#890
1.
b0 ,
0/
1"
#900
0"
#910
b1 ,
1.
1"
#920
0"
#930
1.
b0 ,
b111 0
1/
1"
#940
0"
#950
b1 ,
1.
1"
#960
0"
#970
1.
b0 ,
0/
1"
#980
0"
#990
b1 ,
1.
1"
#1000
0"
#1010
1.
b0 ,
b111 0
1/
1"
#1020
0"
#1030
b1 ,
1.
1"
